{
    "complete": {
        "hidden_channels": 32,
        "layers": 3,
        "heads": 2,
        "augment": true,
        "strategy_prediction": "fit",
        "points_as_features": true,
        "errors_as_features": false,
        "scale": false,
        "strategy_one_hot": "none"
    },
    "predictor": {
        "hidden_channels": 32,
        "layers": 3,
        "heads": 2,
        "strategy_weights": "compute",
        "strategy_sampling": "bernoulli",
        "activation": "softmax",
        "use_ghost_track": false,
        "method": "fit"
    }
}